airchat/__init__.py
airchat/__main__.py
airchat/airchat.py
airchat/cli.py
airchat/utils.py
airchat-0.1.0.dist-info/licenses/LICENSE
airchat-0.1.0.dist-info/METADATA
airchat-0.1.0.dist-info/WHEEL
airchat-0.1.0.dist-info/entry_points.txt
airchat-0.1.0.dist-info/top_level.txt
airchat-0.1.0.dist-info/RECORD
