Metadata-Version: 2.4
Name: airchat
Version: 0.1.0
Summary: A sample chat app for Air
Author-email: Daniel Roy Greenfeld <daniel@feldroy.com>
Maintainer-email: Daniel Roy Greenfeld <daniel@feldroy.com>
License: MIT
Project-URL: bugs, https://github.com/feldroy/airchat/issues
Project-URL: changelog, https://github.com/feldroy/airchat/blob/master/changelog.md
Project-URL: homepage, https://github.com/feldroy/airchat
Requires-Python: >=3.10
License-File: LICENSE
Requires-Dist: typer
Provides-Extra: test
Requires-Dist: coverage; extra == "test"
Requires-Dist: pytest; extra == "test"
Requires-Dist: ruff; extra == "test"
Requires-Dist: ty; extra == "test"
Requires-Dist: ipdb; extra == "test"
Dynamic: license-file
